broker/broker.py
stompy/__init__.py
stompy/client.py
stompy/frame.py
stompy/util.py
stompy/version.py
stompymq-1.1.1.dist-info/LICENSE
stompymq-1.1.1.dist-info/METADATA
stompymq-1.1.1.dist-info/WHEEL
stompymq-1.1.1.dist-info/entry_points.txt
stompymq-1.1.1.dist-info/top_level.txt
stompymq-1.1.1.dist-info/RECORD
