Metadata-Version: 2.1
Name: stompymq
Version: 1.1.1
Summary: Python implementation of STOMP protocol and message broker
Home-page: https://github.com/imandr/stompymq
Author: Igor Mandrichenko
Author-email: igorvm@gmail.com
License: BSD 3-clause
Keywords: STOMP,message queue,message broker
Platform: UNKNOWN
Requires-Dist: pythreader (>=2.5)
